pyristic/__init__.py
pyristic/heuristic/EvolutionStrategy_search.py
pyristic/heuristic/EvolutiveProgramming_search.py
pyristic/heuristic/GeneticAlgorithm_search.py
pyristic/heuristic/SimulatedAnnealing_search.py
pyristic/heuristic/Tabu_search.py
pyristic/heuristic/__init__.py
pyristic/utils/__init__.py
pyristic/utils/helpers.py
pyristic/utils/test_function.py
pyristic/utils/operators/__init__.py
pyristic/utils/operators/crossover.py
pyristic/utils/operators/mutation.py
pyristic/utils/operators/selection.py
pyristic-0.1.4.dist-info/LICENSE
pyristic-0.1.4.dist-info/METADATA
pyristic-0.1.4.dist-info/WHEEL
pyristic-0.1.4.dist-info/top_level.txt
pyristic-0.1.4.dist-info/RECORD
