Metadata-Version: 2.1
Name: pyristic
Version: 0.1.4
Summary: Set of metaheuristic for solve optimization problems.
Home-page: https://github.com/JAOP1/
Author: Jesús Armando Ortíz Peñafiel
Author-email: armandopenafiel12@gmail.com
License: MIT
Download-URL: https://github.com/JAOP1/pyristic/archive/refs/tags/0.1.4.tar.gz
Keywords: Optimization,Metaheuristic,Python
Platform: UNKNOWN
Classifier: Development Status :: 3 - Alpha
Classifier: Intended Audience :: Developers
Classifier: Intended Audience :: Science/Research
Classifier: Topic :: Software Development :: Build Tools
Classifier: License :: OSI Approved :: MIT License
Classifier: Programming Language :: Python :: 3.7
License-File: LICENSE
Requires-Dist: numpy (>=1.15.4)
Requires-Dist: tqdm (>=4.28.1)
Requires-Dist: numba (==0.51.0)
